[
  {
    "id": "nt",
    "contentUri": "coremedia://collection/5555990",
    "dataLayerPrepared": {
      "uri": "coremedia://collection/5555990",
      "moduleUri": "app://module/news-homepage-topstories-nt",
      "contentSource": "coremedia",
      "contentType": "collection",
      "id": "5555990",
      "title": {
        "title": "Top Stories"
      },
      "items": [
        {
          "uri": "coremedia://article/105856034"
        },
        {
          "uri": "coremedia://article/105842404"
        },
        {
          "uri": "coremedia://article/105859708"
        },
        {
          "uri": "coremedia://article/105747486"
        },
        {
          "uri": "coremedia://article/105844344"
        },
        {
          "uri": "coremedia://article/105848692"
        },
        {
          "uri": "coremedia://article/105840336"
        },
        {
          "uri": "coremedia://article/105860720"
        },
        {
          "uri": "coremedia://article/105860736"
        },
        {
          "uri": "coremedia://article/105860592"
        },
        {
          "uri": "coremedia://article/105856332"
        },
        {
          "uri": "coremedia://article/105860278"
        },
        {
          "uri": "coremedia://article/105857490"
        },
        {
          "uri": "coremedia://article/105859512"
        },
        {
          "uri": "coremedia://article/105860606"
        },
        {
          "uri": "coremedia://article/105858916"
        },
        {
          "uri": "coremedia://article/105848984"
        },
        {
          "uri": "coremedia://article/105847166"
        },
        {
          "uri": "coremedia://article/105844096"
        },
        {
          "uri": "coremedia://article/105860520"
        },
        {
          "uri": "coremedia://article/105859644"
        },
        {
          "uri": "coremedia://article/105806004"
        },
        {
          "uri": "coremedia://article/105860158"
        },
        {
          "uri": "coremedia://article/105853650"
        },
        {
          "uri": "coremedia://article/105860856"
        },
        {
          "uri": "coremedia://article/105854018"
        },
        {
          "uri": "coremedia://article/105859742"
        },
        {
          "uri": "coremedia://article/105860724"
        },
        {
          "uri": "coremedia://article/105829904"
        },
        {
          "uri": "coremedia://article/105860646"
        },
        {
          "uri": "coremedia://article/105833458"
        },
        {
          "uri": "coremedia://article/105856064"
        },
        {
          "uri": "coremedia://article/105860698"
        },
        {
          "uri": "coremedia://article/105859764"
        },
        {
          "uri": "coremedia://article/105858164"
        }
      ]
    },
    "items": [
      {
        "name": "VolumeCard",
        "props": {
          "contentLabels": [],
          "headingClassNames": [],
          "id": "105856034",
          "imagePosition": {
            "mobile": "right",
            "tablet": "left",
            "desktop": "left"
          },
          "isMajor": false,
          "image": {
            "altText": "An aerial shot of a construction site near the ocean's edge, cranes can be seen below.",
            "imgSrc": "https://live-production.wcms.abc-cdn.net.au/be358f66d917a018ec544cb7164ad7a9?impolicy=wcms_crop_resize&cropH=2328&cropW=3492&xPos=378&yPos=369&width=160&height=107",
            "imgRatio": "3x2"
          },
          "link": {
            "to": "/news/2025-10-07/nt-taxpayers-billion-dollar-ship-lift-pearling-giant-paspaley/105856034"
          },
          "contentUri": "coremedia://article/105856034",
          "canonicalURL": "https://www.abc.net.au/news/2025-10-07/nt-taxpayers-billion-dollar-ship-lift-pearling-giant-paspaley/105856034",
          "video": null,
          "reactKey": "nt-105856034-1",
          "synopsis": "It’s taken 10 years, blown out by hundreds of millions of dollars, and is still nowhere near becoming operational. Now there are calls for the Darwin ship lift project to be scrapped.",
          "title": {
            "children": "Ship lift project dubbed 'one of the biggest blow-outs' in Australia"
          },
          "imageContainerClassNames": []
        }
      },
      {
        "name": "VolumeCard",
        "props": {
          "contentLabels": [],
          "headingClassNames": [],
          "id": "105842404",
          "imagePosition": {
            "mobile": "right",
            "tablet": "left",
            "desktop": "left"
          },
          "isMajor": false,
          "image": {
            "altText": "A man with a moustache and goatee and wearing a cap standing in front of a building and smiling. ",
            "imgSrc": "https://live-production.wcms.abc-cdn.net.au/21550e4fa99161ae7a6501139a2ab4ce?impolicy=wcms_crop_resize&cropH=533&cropW=800&xPos=0&yPos=353&width=160&height=107",
            "imgRatio": "3x2"
          },
          "link": {
            "to": "/news/2025-10-06/nt-darwin-man-timothy-hunt-convicted-murder-tony-rowe/105842404"
          },
          "contentUri": "coremedia://article/105842404",
          "canonicalURL": "https://www.abc.net.au/news/2025-10-06/nt-darwin-man-timothy-hunt-convicted-murder-tony-rowe/105842404",
          "video": null,
          "reactKey": "nt-105842404-1",
          "synopsis": "Darwin man Timothy Hunt has been convicted of murdering Tony Rowe, whose remains were found on the city's outskirts in May 2023, one year after he was reported missing. ",
          "title": {
            "children": "Darwin man convicted of friend's murder after remains found on city's outskirts"
          },
          "imageContainerClassNames": []
        }
      },
      {
        "name": "VolumeCard",
        "props": {
          "contentLabels": [],
          "headingClassNames": [],
          "id": "105859708",
          "imagePosition": {
            "mobile": "right",
            "tablet": "left",
            "desktop": "left"
          },
          "isMajor": false,
          "image": {
            "altText": "A damaged shop door",
            "imgSrc": "https://live-production.wcms.abc-cdn.net.au/b706e37ecfc2b462b6dcb510ceb77c6c?impolicy=wcms_crop_resize&cropH=3333&cropW=5000&xPos=0&yPos=0&width=160&height=107",
            "imgRatio": "3x2"
          },
          "link": {
            "to": "/news/2025-10-06/man-allegedly-drives-ute-towards-woman-baby-in-alice-springs/105859450"
          },
          "contentUri": "coremedia://article/105859708",
          "canonicalURL": "https://www.abc.net.au/news/2025-10-06/man-allegedly-drives-ute-towards-woman-baby-in-alice-springs/105859450",
          "video": null,
          "reactKey": "nt-105859708-1",
          "synopsis": "A man is in police custody after allegedly driving a ute towards a woman and baby outside a shop in Alice Springs on Monday.",
          "title": {
            "children": "Ute narrowly misses woman, baby in alleged domestic violence attack"
          },
          "imageContainerClassNames": []
        }
      },
      {
        "name": "VolumeCard",
        "props": {
          "contentLabels": [],
          "headingClassNames": [],
          "id": "105747486",
          "imagePosition": {
            "mobile": "right",
            "tablet": "left",
            "desktop": "left"
          },
          "isMajor": false,
          "image": {
            "altText": "A man with grey hair and a beard wearing a blue shirt sits in a chair",
            "imgSrc": "https://live-production.wcms.abc-cdn.net.au/d2db1951b7a00fe3a10e5ba49e385ae7?impolicy=wcms_crop_resize&cropH=3333&cropW=5000&xPos=0&yPos=0&width=160&height=107",
            "imgRatio": "3x2"
          },
          "link": {
            "to": "/news/2025-10-06/calls-for-nt-ban-on-machetes-and-crossbows/105747486"
          },
          "contentUri": "coremedia://article/105747486",
          "canonicalURL": "https://www.abc.net.au/news/2025-10-06/calls-for-nt-ban-on-machetes-and-crossbows/105747486",
          "video": null,
          "reactKey": "nt-105747486-1",
          "synopsis": "There are growing calls for the NT government to ban machetes and crossbows as older residents share horror stories of being targeted in their own homes by armed youths.",
          "title": {
            "children": "'I fought back as best I could': Older Territorians share home invasion horror stories"
          },
          "imageContainerClassNames": []
        }
      },
      {
        "name": "VolumeCard",
        "props": {
          "contentLabels": [],
          "headingClassNames": [],
          "id": "105844344",
          "imagePosition": {
            "mobile": "right",
            "tablet": "left",
            "desktop": "left"
          },
          "isMajor": false,
          "image": {
            "altText": "A fifty and hundred dollar notes sit in red dirt",
            "imgSrc": "https://live-production.wcms.abc-cdn.net.au/6901866ca61321e0a8c87262a198bb99?impolicy=wcms_crop_resize&cropH=2752&cropW=4128&xPos=0&yPos=49&width=160&height=107",
            "imgRatio": "3x2"
          },
          "link": {
            "to": "/news/2025-10-06/outback-wa-retailers-worried-about-centrepay-reforms/105844344"
          },
          "contentUri": "coremedia://article/105844344",
          "canonicalURL": "https://www.abc.net.au/news/2025-10-06/outback-wa-retailers-worried-about-centrepay-reforms/105844344",
          "video": null,
          "reactKey": "nt-105844344-1",
          "synopsis": "Business owners worry major changes to a buy now, pay later system used by about 500,000 social security recipients will cause a raft of issues when it begins next month.",
          "title": {
            "children": "'Risk of losing lots of money': Outback stores slam Centrepay changes"
          },
          "imageContainerClassNames": []
        }
      },
      {
        "name": "VolumeCard",
        "props": {
          "contentLabels": [],
          "headingClassNames": [],
          "id": "105848692",
          "imagePosition": {
            "mobile": "right",
            "tablet": "left",
            "desktop": "left"
          },
          "isMajor": false,
          "image": {
            "altText": "An office building with at least seven floors. The building has multi-coloured cladding.",
            "imgSrc": "https://live-production.wcms.abc-cdn.net.au/1ba799a8ec5a22a68adc1d8f82c9b020?impolicy=wcms_crop_resize&cropH=1080&cropW=1620&xPos=180&yPos=0&width=160&height=107",
            "imgRatio": "3x2"
          },
          "link": {
            "to": "/news/2025-10-06/nt-betting-regulator-accused-close-industry-four-corners/105848692"
          },
          "contentUri": "coremedia://article/105848692",
          "canonicalURL": "https://www.abc.net.au/news/2025-10-06/nt-betting-regulator-accused-close-industry-four-corners/105848692",
          "video": null,
          "reactKey": "nt-105848692-1",
          "synopsis": "Four Corners has uncovered allegations of conflicts of interest and pro-industry bias at the country's part-time regulator responsible for Australia's biggest betting companies. ",
          "title": {
            "children": "Gambling regulator's alleged 'cosy relationship' with $50b betting industry"
          },
          "imageContainerClassNames": []
        }
      },
      {
        "name": "VolumeCard",
        "props": {
          "contentLabels": [],
          "headingClassNames": [],
          "id": "105840336",
          "imagePosition": {
            "mobile": "right",
            "tablet": "left",
            "desktop": "left"
          },
          "isMajor": false,
          "image": {
            "altText": "Drone image of Elcho Island.",
            "imgSrc": "https://live-production.wcms.abc-cdn.net.au/36b0755dab603a170e5459b0c1bb4a6f?impolicy=wcms_crop_resize&cropH=2214&cropW=3321&xPos=308&yPos=0&width=160&height=107",
            "imgRatio": "3x2"
          },
          "link": {
            "to": "/news/2025-10-05/nt-hepatitis-b-diagnoses-rising-as-mortality-rates-decrease/105840336"
          },
          "contentUri": "coremedia://article/105840336",
          "canonicalURL": "https://www.abc.net.au/news/2025-10-05/nt-hepatitis-b-diagnoses-rising-as-mortality-rates-decrease/105840336",
          "video": null,
          "reactKey": "nt-105840336-1",
          "synopsis": "Health workers say new data showing hepatitis B cases have almost tripled in the NT reflects better access to care, with the territory also leading the nation in reducing mortality rates.",
          "title": {
            "children": "Hepatitis B cases are rising in the NT, but experts say it's a positive sign"
          },
          "imageContainerClassNames": []
        }
      },
      {
        "name": "VolumeCard",
        "props": {
          "contentLabels": [],
          "headingClassNames": [],
          "id": "105860720",
          "imagePosition": {
            "mobile": "right",
            "tablet": "left",
            "desktop": "left"
          },
          "isMajor": false,
          "image": {
            "altText": "Sussan Ley in press conference",
            "imgSrc": "https://live-production.wcms.abc-cdn.net.au/e293d72765ee73e316e61f4870ac4f74?impolicy=wcms_crop_resize&cropH=4480&cropW=6720&xPos=0&yPos=0&width=160&height=107",
            "imgRatio": "3x2"
          },
          "link": {
            "to": "/news/2025-10-07/coalition-minimum-sentencing-child-abuse-trans-debate-maloney/105858528"
          },
          "contentUri": "coremedia://article/105860720",
          "canonicalURL": "https://www.abc.net.au/news/2025-10-07/coalition-minimum-sentencing-child-abuse-trans-debate-maloney/105858528",
          "video": null,
          "reactKey": "nt-105860720-1",
          "synopsis": "Opposition Leader Sussan Ley raises the case of a trans child abuser as she seeks to pressure the Albanese government to create mandatory minimum jail terms for child exploitation offences. ",
          "title": {
            "children": "Coalition tries to wedge Labor on mandatory child abuse sentencing"
          },
          "imageContainerClassNames": []
        }
      },
      {
        "name": "VolumeCard",
        "props": {
          "contentLabels": [],
          "headingClassNames": [],
          "id": "105860736",
          "imagePosition": {
            "mobile": "right",
            "tablet": "left",
            "desktop": "left"
          },
          "isMajor": false,
          "image": {
            "altText": "A woman with brown hair wearing a pink blouse sitting on a couch in a TV studio",
            "imgSrc": "https://live-production.wcms.abc-cdn.net.au/b7ca263d760accf86fbc47b98c803170?impolicy=wcms_crop_resize&cropH=637&cropW=956&xPos=132&yPos=0&width=160&height=107",
            "imgRatio": "3x2"
          },
          "link": {
            "to": "/news/2025-10-07/woman-claiming-to-be-madeleine-mccann-stalked-parents-uk-court/105860736"
          },
          "contentUri": "coremedia://article/105860736",
          "canonicalURL": "https://www.abc.net.au/news/2025-10-07/woman-claiming-to-be-madeleine-mccann-stalked-parents-uk-court/105860736",
          "video": null,
          "reactKey": "nt-105860736-1",
          "synopsis": "A 24-year-old woman who claims to be Madeleine McCann is on trial charged with stalking the missing child's parents over the past three years. ",
          "title": {
            "children": "Woman claiming to be Madeleine McCann faces court"
          },
          "imageContainerClassNames": []
        }
      },
      {
        "name": "VolumeCard",
        "props": {
          "contentLabels": [],
          "headingClassNames": [],
          "id": "105860592",
          "imagePosition": {
            "mobile": "right",
            "tablet": "left",
            "desktop": "left"
          },
          "isMajor": false,
          "image": {
            "altText": "Two US soldiers in fatigues, face covered, sunglasses, crouch on the road, holding a person down, smoke visible in background.",
            "imgSrc": "https://live-production.wcms.abc-cdn.net.au/e268538462004e214e4b5a072a2151ec?impolicy=wcms_crop_resize&cropH=3333&cropW=5000&xPos=0&yPos=0&width=160&height=107",
            "imgRatio": "3x2"
          },
          "link": {
            "to": "/news/2025-10-07/chicago-and-illinois-sue-trump-to-stop-national-guard-deployment/105860592"
          },
          "contentUri": "coremedia://article/105860592",
          "canonicalURL": "https://www.abc.net.au/news/2025-10-07/chicago-and-illinois-sue-trump-to-stop-national-guard-deployment/105860592",
          "video": null,
          "reactKey": "nt-105860592-1",
          "synopsis": "Illinois is suing to block Donald Trump’s troop deployment to Chicago in what will be the president's fourth legal challenge over federal use of National Guard in cities.",
          "title": {
            "children": "Illinois sues to stop National Guard in Chicago after court victory"
          },
          "imageContainerClassNames": []
        }
      },
      {
        "name": "VolumeCard",
        "props": {
          "contentLabels": [],
          "headingClassNames": [],
          "id": "105856332",
          "imagePosition": {
            "mobile": "right",
            "tablet": "left",
            "desktop": "left"
          },
          "isMajor": false,
          "image": {
            "altText": "A young white man with short brown hair and a blue shirt standing in a Melbourne laneway",
            "imgSrc": "https://live-production.wcms.abc-cdn.net.au/22733b6361528f84b48a541c2cec5acd?impolicy=wcms_crop_resize&cropH=3333&cropW=5000&xPos=0&yPos=0&width=160&height=107",
            "imgRatio": "3x2"
          },
          "link": {
            "to": "/news/2025-10-07/bulk-billing-low-as-gps-spend-longer-with-patients-racgp/105856332"
          },
          "contentUri": "coremedia://article/105856332",
          "canonicalURL": "https://www.abc.net.au/news/2025-10-07/bulk-billing-low-as-gps-spend-longer-with-patients-racgp/105856332",
          "video": null,
          "reactKey": "nt-105856332-1",
          "synopsis": "An industry survey finds GPs are managing conditions typically handled by specialists due to high costs and only 12 per cent can afford to bulk-bill all patients.",
          "title": {
            "children": "GP says fees will go up at his clinic when bulk-billing incentives come in"
          },
          "imageContainerClassNames": []
        }
      },
      {
        "name": "VolumeCard",
        "props": {
          "contentLabels": [],
          "headingClassNames": [],
          "id": "105860278",
          "imagePosition": {
            "mobile": "right",
            "tablet": "left",
            "desktop": "left"
          },
          "isMajor": false,
          "image": {
            "altText": "A firefighter carries a hiker out on his back in the dark, with a group of people using head torches.",
            "imgSrc": "https://live-production.wcms.abc-cdn.net.au/d2131dd1c71d1d691beec0a76102faa9?impolicy=wcms_crop_resize&cropH=1506&cropW=2258&xPos=319&yPos=0&width=160&height=107",
            "imgRatio": "3x2"
          },
          "link": {
            "to": "/news/2025-10-07/hundreds-rescued-from-mount-everest-blizzard-as-search-continues/105860278"
          },
          "contentUri": "coremedia://article/105860278",
          "canonicalURL": "https://www.abc.net.au/news/2025-10-07/hundreds-rescued-from-mount-everest-blizzard-as-search-continues/105860278",
          "video": null,
          "reactKey": "nt-105860278-1",
          "synopsis": "Villagers have joined rescue crews in attempting to save those who have become stuck in heavy snow on Mount Everest in Tibet.",
          "title": {
            "children": "Hundreds of hikers still missing after Mount Everest blizzard"
          },
          "imageContainerClassNames": []
        }
      },
      {
        "name": "VolumeCard",
        "props": {
          "contentLabels": [],
          "headingClassNames": [],
          "id": "105857490",
          "imagePosition": {
            "mobile": "right",
            "tablet": "left",
            "desktop": "left"
          },
          "isMajor": false,
          "image": {
            "altText": "A composite image of Megan Fox, Joshua Elmes, Alicia Montebello and Lucus Garzoli",
            "imgSrc": "https://live-production.wcms.abc-cdn.net.au/83fcaf9bfe6301d19336f9f4b852e1de?impolicy=wcms_crop_resize&cropH=533&cropW=800&xPos=0&yPos=0&width=160&height=107",
            "imgRatio": "3x2"
          },
          "link": {
            "to": "/news/2025-10-07/bochara-crash-coroners-report-four-dead/105857490"
          },
          "contentUri": "coremedia://article/105857490",
          "canonicalURL": "https://www.abc.net.au/news/2025-10-07/bochara-crash-coroners-report-four-dead/105857490",
          "video": null,
          "reactKey": "nt-105857490-1",
          "synopsis": "A coroner determines that the sole survivor of a crash that killed four people at Bochara was behind the wheel during the incident.",
          "title": {
            "children": "Coroner's warning on crash that killed adult and three teens"
          },
          "imageContainerClassNames": []
        }
      },
      {
        "name": "VolumeCard",
        "props": {
          "contentLabels": [],
          "headingClassNames": [],
          "id": "105859512",
          "imagePosition": {
            "mobile": "right",
            "tablet": "left",
            "desktop": "left"
          },
          "isMajor": false,
          "image": {
            "altText": "A man in a suit holds a press conference with a concerned expression.",
            "imgSrc": "https://live-production.wcms.abc-cdn.net.au/23062313341b6720a278bacd63f9378f?impolicy=wcms_crop_resize&cropH=3333&cropW=5000&xPos=0&yPos=0&width=160&height=107",
            "imgRatio": "3x2"
          },
          "link": {
            "to": "/news/2025-10-06/french-pm-sebastien-lecornu-resigns/105859512"
          },
          "contentUri": "coremedia://article/105859512",
          "canonicalURL": "https://www.abc.net.au/news/2025-10-06/french-pm-sebastien-lecornu-resigns/105859512",
          "video": null,
          "reactKey": "nt-105859512-1",
          "synopsis": "Mr Lecornu stepped down just 14 hours after naming his Cabinet, plunging France into another political crisis.",
          "title": {
            "children": "Macron gives French PM days to save administration after snap resignation"
          },
          "imageContainerClassNames": []
        }
      },
      {
        "name": "VolumeCard",
        "props": {
          "contentLabels": [],
          "headingClassNames": [],
          "id": "105860606",
          "imagePosition": {
            "mobile": "right",
            "tablet": "left",
            "desktop": "left"
          },
          "isMajor": false,
          "image": {
            "altText": "The supermoon as it rises over Mt Coot-tha in Brisbane.",
            "imgSrc": "https://live-production.wcms.abc-cdn.net.au/ba00c45f904ed52e581922c4929e4799?impolicy=wcms_crop_resize&cropH=646&cropW=970&xPos=0&yPos=102&width=160&height=107",
            "imgRatio": "3x2"
          },
          "link": {
            "to": "/news/science/2025-10-07/harvest-full-moon-supermoon-season-perigee-orbit-tides/105840108"
          },
          "contentUri": "coremedia://article/105860606",
          "canonicalURL": "https://www.abc.net.au/news/science/2025-10-07/harvest-full-moon-supermoon-season-perigee-orbit-tides/105840108",
          "video": null,
          "reactKey": "nt-105860606-1",
          "synopsis": "Our skies will be graced by up to four consecutive supermoons over the next months. Here's why they happen, and how we can end up with multiple supermoons in a row.",
          "title": {
            "children": "A trifecta of supermoons starts with tonight's harvest moon"
          },
          "imageContainerClassNames": []
        }
      },
      {
        "name": "VolumeCard",
        "props": {
          "contentLabels": [],
          "headingClassNames": [],
          "id": "105858916",
          "imagePosition": {
            "mobile": "right",
            "tablet": "left",
            "desktop": "left"
          },
          "isMajor": false,
          "image": {
            "altText": "Dozens of birds on the sand next to waves at a beach. ",
            "imgSrc": "https://live-production.wcms.abc-cdn.net.au/c822b86be85ca0975c92f4fd8319e7c2?impolicy=wcms_crop_resize&cropH=1206&cropW=1809&xPos=374&yPos=312&width=160&height=107",
            "imgRatio": "3x2"
          },
          "link": {
            "to": "/news/2025-10-07/rob-blakers-pleads-guilty-to-trespassing-charges-robbins-island/105858916"
          },
          "contentUri": "coremedia://article/105858916",
          "canonicalURL": "https://www.abc.net.au/news/2025-10-07/rob-blakers-pleads-guilty-to-trespassing-charges-robbins-island/105858916",
          "video": null,
          "reactKey": "nt-105858916-1",
          "synopsis": "Wildlife photographer Rob Blakers pleads guilty to trespassing after admitting he camped beyond the boundary line whilst visiting privately owned Robbins Island to observe migratory birds.",
          "title": {
            "children": "Renowned photographer tried to avoid trespass by staying below high-tide mark"
          },
          "imageContainerClassNames": []
        }
      },
      {
        "name": "VolumeCard",
        "props": {
          "contentLabels": [],
          "headingClassNames": [],
          "id": "105848984",
          "imagePosition": {
            "mobile": "right",
            "tablet": "left",
            "desktop": "left"
          },
          "isMajor": false,
          "image": {
            "altText": "An empty potato shelf at Woolworths in South Australia.",
            "imgSrc": "https://live-production.wcms.abc-cdn.net.au/753dac46159d0de8b77ac161c2cbf5f5?impolicy=wcms_crop_resize&cropH=2567&cropW=3851&xPos=0&yPos=244&width=160&height=107",
            "imgRatio": "3x2"
          },
          "link": {
            "to": "/news/rural/2025-10-07/potato-shortage-as-farmers-battle-weather-extremes/105848984"
          },
          "contentUri": "coremedia://article/105848984",
          "canonicalURL": "https://www.abc.net.au/news/rural/2025-10-07/potato-shortage-as-farmers-battle-weather-extremes/105848984",
          "video": null,
          "reactKey": "nt-105848984-1",
          "synopsis": "South Australia produces 80 per cent of Australia's fresh potatoes, but extreme weather and drought across the state are causing a major shortage. ",
          "title": {
            "children": "Customers face empty shelves as farmers battle potato shortage"
          },
          "imageContainerClassNames": []
        }
      },
      {
        "name": "VolumeCard",
        "props": {
          "contentLabels": [],
          "headingClassNames": [],
          "id": "105847166",
          "imagePosition": {
            "mobile": "right",
            "tablet": "left",
            "desktop": "left"
          },
          "isMajor": false,
          "image": {
            "altText": "a man in a dark jacket walks through a brown crop",
            "imgSrc": "https://live-production.wcms.abc-cdn.net.au/38a2e270e5d0ad1e23380b69e5fa83da?impolicy=wcms_crop_resize&cropH=3333&cropW=5000&xPos=0&yPos=0&width=160&height=107",
            "imgRatio": "3x2"
          },
          "link": {
            "to": "/news/2025-10-07/bayer-announces-plans-for-australian-rollout-of-new-weed-killer/105847166"
          },
          "contentUri": "coremedia://article/105847166",
          "canonicalURL": "https://www.abc.net.au/news/2025-10-07/bayer-announces-plans-for-australian-rollout-of-new-weed-killer/105847166",
          "video": null,
          "reactKey": "nt-105847166-1",
          "synopsis": "We've been spraying it on our farms, gardens and roadsides for 50 years, but the world's most used weedkiller is starting to run out of steam. But after 10 years and hundreds of millions of dollars in R&D, Roundup's owner says it has an alternative. ",
          "title": {
            "children": "German chemical giant to release Roundup alternative in Australia"
          },
          "imageContainerClassNames": []
        }
      },
      {
        "name": "VolumeCard",
        "props": {
          "contentLabels": [],
          "headingClassNames": [],
          "id": "105844096",
          "imagePosition": {
            "mobile": "right",
            "tablet": "left",
            "desktop": "left"
          },
          "isMajor": false,
          "image": {
            "altText": "Janine Vaughan smiling and wearing a dress.",
            "imgSrc": "https://live-production.wcms.abc-cdn.net.au/7f8eff8948992786ccdc49ec59be2aad?impolicy=wcms_crop_resize&cropH=666&cropW=999&xPos=0&yPos=49&width=160&height=107",
            "imgRatio": "3x2"
          },
          "link": {
            "to": "/news/2025-10-07/janine-vaughan-bathurst-1000-missing-persons-billboard-dispute/105844096"
          },
          "contentUri": "coremedia://article/105844096",
          "canonicalURL": "https://www.abc.net.au/news/2025-10-07/janine-vaughan-bathurst-1000-missing-persons-billboard-dispute/105844096",
          "video": null,
          "reactKey": "nt-105844096-1",
          "synopsis": "With more than 200,000 people expected to attend this weekend's Bathurst 1000, the family of Janine Vaughan wants a billboard raising awareness about her disappearance uncovered.  ",
          "title": {
            "children": "Family of missing woman hopes Bathurst 1000 can uncover answers"
          },
          "imageContainerClassNames": []
        }
      },
      {
        "name": "VolumeCard",
        "props": {
          "contentLabels": [],
          "headingClassNames": [],
          "id": "105860520",
          "imagePosition": {
            "mobile": "right",
            "tablet": "left",
            "desktop": "left"
          },
          "isMajor": false,
          "image": {
            "altText": "A woman sits a court deck. ",
            "imgSrc": "https://live-production.wcms.abc-cdn.net.au/da0ee9ccefb4ef62a62072f0f99260f6?impolicy=wcms_crop_resize&cropH=2366&cropW=3549&xPos=1&yPos=0&width=160&height=107",
            "imgRatio": "3x2"
          },
          "link": {
            "to": "/news/2025-10-07/gis%C3%A8le-pelicot-to-face-rapist-once-again-in-french-appeals-case/105859998"
          },
          "contentUri": "coremedia://article/105860520",
          "canonicalURL": "https://www.abc.net.au/news/2025-10-07/gis%C3%A8le-pelicot-to-face-rapist-once-again-in-french-appeals-case/105859998",
          "video": null,
          "reactKey": "nt-105860520-1",
          "synopsis": "Less than a year after the landmark trial which shook the world, Gisèle Pelicot will once again brave a courtroom as one of her rapists appeals his sentence.",
          "title": {
            "children": "Gisèle Pelicot to face rapist once again in French appeals case"
          },
          "imageContainerClassNames": []
        }
      },
      {
        "name": "VolumeCard",
        "props": {
          "contentLabels": [],
          "headingClassNames": [],
          "id": "105859644",
          "imagePosition": {
            "mobile": "right",
            "tablet": "left",
            "desktop": "left"
          },
          "isMajor": false,
          "image": {
            "altText": "Col Blanch standing in front of a building speaking.",
            "imgSrc": "https://live-production.wcms.abc-cdn.net.au/81bfe6add0deb48b2da326eb0883eafd?impolicy=wcms_crop_resize&cropH=2666&cropW=4000&xPos=0&yPos=1&width=160&height=107",
            "imgRatio": "3x2"
          },
          "link": {
            "to": "/news/2025-10-07/wa-sovereign-citizen-gun-raids-fears-dramatic-response/105859644"
          },
          "contentUri": "coremedia://article/105859644",
          "canonicalURL": "https://www.abc.net.au/news/2025-10-07/wa-sovereign-citizen-gun-raids-fears-dramatic-response/105859644",
          "video": null,
          "reactKey": "nt-105859644-1",
          "synopsis": "A radicalisation expert warns a crackdown on gun-owning \"sovereign citizens\" in West Australia risks further entrenching extremist views in an already disenfranchised group.",
          "title": {
            "children": "Fears gun raids on sovereign citizens could raise threat level"
          },
          "imageContainerClassNames": []
        }
      },
      {
        "name": "VolumeCard",
        "props": {
          "contentLabels": [],
          "headingClassNames": [],
          "id": "105806004",
          "imagePosition": {
            "mobile": "right",
            "tablet": "left",
            "desktop": "left"
          },
          "isMajor": false,
          "image": {
            "altText": "A woman holding an AFP report into the sovereign citizen movement while looking at the Facebook login screen",
            "imgSrc": "https://live-production.wcms.abc-cdn.net.au/57a7b2fb32670193d589b13f90f6ac51?impolicy=wcms_crop_resize&cropH=3333&cropW=5000&xPos=0&yPos=0&width=160&height=107",
            "imgRatio": "3x2"
          },
          "link": {
            "to": "/news/2025-10-07/calls-for-sovereign-citizens-to-be-classified-as-terrorists/105806004"
          },
          "contentUri": "coremedia://article/105806004",
          "canonicalURL": "https://www.abc.net.au/news/2025-10-07/calls-for-sovereign-citizens-to-be-classified-as-terrorists/105806004",
          "video": null,
          "reactKey": "nt-105806004-1",
          "synopsis": "A man who says he was threatened after investigating sovereign citizens says the movement should be labelled a terrorist organisation, but an academic argues this could lead to more violence.",
          "title": {
            "children": "Doxed man petitions to have sovereign citizens declared domestic terrorists"
          },
          "imageContainerClassNames": []
        }
      },
      {
        "name": "VolumeCard",
        "props": {
          "contentLabels": [],
          "headingClassNames": [],
          "id": "105860158",
          "imagePosition": {
            "mobile": "right",
            "tablet": "left",
            "desktop": "left"
          },
          "isMajor": false,
          "image": {
            "altText": "A sign with a photo of Epstein and Maxwell, urging peole to call if they have been a victim, is pointed to.",
            "imgSrc": "https://live-production.wcms.abc-cdn.net.au/4316d2cf03df9ba325a15e74e53897fc?impolicy=wcms_crop_resize&cropH=3253&cropW=4880&xPos=0&yPos=0&width=160&height=107",
            "imgRatio": "3x2"
          },
          "link": {
            "to": "/news/2025-10-07/supreme-court-rejects-appeal-from-ghislaine-maxwell/105860158"
          },
          "contentUri": "coremedia://article/105860158",
          "canonicalURL": "https://www.abc.net.au/news/2025-10-07/supreme-court-rejects-appeal-from-ghislaine-maxwell/105860158",
          "video": null,
          "reactKey": "nt-105860158-1",
          "synopsis": "The US Supreme Court declines to hear Ghislaine Maxwell's bid to overturn her conviction for helping the late financier and convicted sex offender Jeffrey Epstein sexually abuse teenage girls.",
          "title": {
            "children": "US court declines Ghislaine Maxwell appeal against sex trafficking conviction"
          },
          "imageContainerClassNames": []
        }
      },
      {
        "name": "VolumeCard",
        "props": {
          "contentLabels": [],
          "headingClassNames": [],
          "id": "105853650",
          "imagePosition": {
            "mobile": "right",
            "tablet": "left",
            "desktop": "left"
          },
          "isMajor": false,
          "image": {
            "altText": "Firefighters battling urban bushfire",
            "imgSrc": "https://live-production.wcms.abc-cdn.net.au/ef71c09d1f670c0f683f94a230dcc26e?impolicy=wcms_crop_resize&cropH=3712&cropW=5568&xPos=0&yPos=0&width=160&height=107",
            "imgRatio": "3x2"
          },
          "link": {
            "to": "/news/2025-10-07/wildfires-more-lethal-economically-damaging-report-finds/105853650"
          },
          "contentUri": "coremedia://article/105853650",
          "canonicalURL": "https://www.abc.net.au/news/2025-10-07/wildfires-more-lethal-economically-damaging-report-finds/105853650",
          "video": null,
          "reactKey": "nt-105853650-1",
          "synopsis": "New Australian research shows, globally, major bushfire events are becoming more frequent, fatal and economically damaging. ",
          "title": {
            "children": "Australia's south coast 'very, very high risk' for bushfires, modelling shows"
          },
          "imageContainerClassNames": []
        }
      },
      {
        "name": "VolumeCard",
        "props": {
          "contentLabels": [],
          "headingClassNames": [],
          "id": "105860856",
          "imagePosition": {
            "mobile": "right",
            "tablet": "left",
            "desktop": "left"
          },
          "isMajor": false,
          "image": {
            "altText": "An SES volunteer in orange overalls walks across grassland towards a row of SES and police vehicles",
            "imgSrc": "https://live-production.wcms.abc-cdn.net.au/de15fafc6c0d2e8a7d4513af21413343?impolicy=wcms_crop_resize&cropH=922&cropW=1383&xPos=20&yPos=0&width=160&height=107",
            "imgRatio": "3x2"
          },
          "link": {
            "to": "/news/2025-10-07/gus-missing-boy-facebook-ai-misinformation/105856594"
          },
          "contentUri": "coremedia://article/105860856",
          "canonicalURL": "https://www.abc.net.au/news/2025-10-07/gus-missing-boy-facebook-ai-misinformation/105856594",
          "video": null,
          "reactKey": "nt-105860856-1",
          "synopsis": "Users have reported Facebook's AI search has shown incorrect information about four-year-old Gus who remains missing in SA's outback.",
          "title": {
            "children": "Expert cautions AI use as it gives misinformation about missing SA boy"
          },
          "imageContainerClassNames": []
        }
      },
      {
        "name": "VolumeCard",
        "props": {
          "contentLabels": [],
          "headingClassNames": [],
          "id": "105854018",
          "imagePosition": {
            "mobile": "right",
            "tablet": "left",
            "desktop": "left"
          },
          "isMajor": false,
          "image": {
            "altText": "Arlo and Marlin Malpass",
            "imgSrc": "https://live-production.wcms.abc-cdn.net.au/cdc6512f5345603d901aa40c962b22e0?impolicy=wcms_crop_resize&cropH=4000&cropW=6000&xPos=0&yPos=0&width=160&height=107",
            "imgRatio": "3x2"
          },
          "link": {
            "to": "/news/2025-10-07/childcare-children-with-disability-pilot-program-trial-perth/105854018"
          },
          "contentUri": "coremedia://article/105854018",
          "canonicalURL": "https://www.abc.net.au/news/2025-10-07/childcare-children-with-disability-pilot-program-trial-perth/105854018",
          "video": null,
          "reactKey": "nt-105854018-1",
          "synopsis": "An Australian-first pilot program gets underway in WA in the hope of not only giving the parents of children with complex needs a break, but helping them navigate the maze of different support systems. ",
          "title": {
            "children": "New program allows parents of kids with complex needs to take a break"
          },
          "imageContainerClassNames": []
        }
      },
      {
        "name": "VolumeCard",
        "props": {
          "contentLabels": [],
          "headingClassNames": [],
          "id": "105859742",
          "imagePosition": {
            "mobile": "right",
            "tablet": "left",
            "desktop": "left"
          },
          "isMajor": false,
          "image": {
            "altText": "A PowerPoint showing the three scientists with their faces, biography and a headshot",
            "imgSrc": "https://live-production.wcms.abc-cdn.net.au/705c22e5fc5c317493b8cc80ed3b6768?impolicy=wcms_crop_resize&cropH=3333&cropW=5000&xPos=0&yPos=0&width=160&height=107",
            "imgRatio": "3x2"
          },
          "link": {
            "to": "/news/2025-10-06/scientists-win-nobel-prize-medicine-for-immune-system-work/105859742"
          },
          "contentUri": "coremedia://article/105859742",
          "canonicalURL": "https://www.abc.net.au/news/2025-10-06/scientists-win-nobel-prize-medicine-for-immune-system-work/105859742",
          "video": null,
          "reactKey": "nt-105859742-1",
          "synopsis": "The Nobel Prize for Medicine has been given to three scientists for discovering how our immune systems protect us from microbes.",
          "title": {
            "children": "Trio of scientists win Nobel Prize in Medicine for work on immune system"
          },
          "imageContainerClassNames": []
        }
      },
      {
        "name": "VolumeCard",
        "props": {
          "contentLabels": [],
          "headingClassNames": [],
          "id": "105860724",
          "imagePosition": {
            "mobile": "right",
            "tablet": "left",
            "desktop": "left"
          },
          "isMajor": false,
          "image": {
            "altText": "A woman in a pantsuit sits on a chair next to a table of books. ",
            "imgSrc": "https://live-production.wcms.abc-cdn.net.au/93348fe7863375e047bc72200e236c29?impolicy=wcms_crop_resize&cropH=2333&cropW=3499&xPos=0&yPos=0&width=160&height=107",
            "imgRatio": "3x2"
          },
          "link": {
            "to": "/news/2025-10-06/author-jilly-cooper-dies-at-age-88/105859754"
          },
          "contentUri": "coremedia://article/105860724",
          "canonicalURL": "https://www.abc.net.au/news/2025-10-06/author-jilly-cooper-dies-at-age-88/105859754",
          "video": null,
          "reactKey": "nt-105860724-1",
          "synopsis": "The author was best known for The Rutshire Chronicles, including the novel Rivals, which was recently adapted into a Disney+ series.",
          "title": {
            "children": "Jilly Cooper, English author known for her 'bonkbusters' dies at age 88"
          },
          "imageContainerClassNames": []
        }
      },
      {
        "name": "VolumeCard",
        "props": {
          "contentLabels": [],
          "headingClassNames": [],
          "id": "105829904",
          "imagePosition": {
            "mobile": "right",
            "tablet": "left",
            "desktop": "left"
          },
          "isMajor": false,
          "image": {
            "altText": "An image of Callan Park, a sandstone building with parkland, in the background + two old black and white pics of the building.",
            "imgSrc": "https://live-production.wcms.abc-cdn.net.au/ad617b22fd8afd44ae0f8010a4477b8b?impolicy=wcms_crop_resize&cropH=1080&cropW=1620&xPos=300&yPos=0&width=160&height=107",
            "imgRatio": "3x2"
          },
          "link": {
            "to": "/news/2025-10-07/future-for-sydney-former-psychiatric-hospital-sites-callan-park/105829904"
          },
          "contentUri": "coremedia://article/105829904",
          "canonicalURL": "https://www.abc.net.au/news/2025-10-07/future-for-sydney-former-psychiatric-hospital-sites-callan-park/105829904",
          "video": null,
          "reactKey": "nt-105829904-1",
          "synopsis": "The challenge of transforming a major piece of Sydney's public space from a former mental health hospital to an \"iconic urban parkland\" is a delicate dance for the state government.",
          "title": {
            "children": "Psychiatric hospital to 'urban parkland': Sydney's public space dilemma"
          },
          "imageContainerClassNames": []
        }
      },
      {
        "name": "VolumeCard",
        "props": {
          "contentLabels": [],
          "headingClassNames": [],
          "id": "105860646",
          "imagePosition": {
            "mobile": "right",
            "tablet": "left",
            "desktop": "left"
          },
          "isMajor": false,
          "image": {
            "altText": "A close-up of Daria Kasatkina looking tired and sweating at Wimbledon.",
            "imgSrc": "https://live-production.wcms.abc-cdn.net.au/3658b6e5947dc0079d3bfc95eb8e70b4?impolicy=wcms_crop_resize&cropH=3274&cropW=4911&xPos=0&yPos=0&width=160&height=107",
            "imgRatio": "3x2"
          },
          "link": {
            "to": "/news/2025-10-07/daria-kasatkina-taking-a-break-from-tennis-burnout/105860646"
          },
          "contentUri": "coremedia://article/105860646",
          "canonicalURL": "https://www.abc.net.au/news/2025-10-07/daria-kasatkina-taking-a-break-from-tennis-burnout/105860646",
          "video": null,
          "reactKey": "nt-105860646-1",
          "synopsis": "Daria Kasatkina ends her 2025 WTA season early, citing the hectic schedule and a high-stress year after switching nationalities to Australia from Russia. ",
          "title": {
            "children": "'At breaking point': Aussie star Kasatkina joins tennis's 'tap out club'"
          },
          "imageContainerClassNames": []
        }
      },
      {
        "name": "VolumeCard",
        "props": {
          "contentLabels": [],
          "headingClassNames": [],
          "id": "105833458",
          "imagePosition": {
            "mobile": "right",
            "tablet": "left",
            "desktop": "left"
          },
          "isMajor": false,
          "image": {
            "altText": "A smaller Kangaroo stands in front of a larger kangaroo in high grass. ",
            "imgSrc": "https://live-production.wcms.abc-cdn.net.au/c061ba04b4297f8c4f23be4a5548a126?impolicy=wcms_crop_resize&cropH=3333&cropW=5000&xPos=0&yPos=0&width=160&height=107",
            "imgRatio": "3x2"
          },
          "link": {
            "to": "/news/2025-10-07/drought-kangaroo-populations-impacting-farmers-eating-pastures/105833458"
          },
          "contentUri": "coremedia://article/105833458",
          "canonicalURL": "https://www.abc.net.au/news/2025-10-07/drought-kangaroo-populations-impacting-farmers-eating-pastures/105833458",
          "video": null,
          "reactKey": "nt-105833458-1",
          "synopsis": "Farmers are calling for a cull of kangaroos, which they say are being forced onto farmland by drought and dry conditions and consuming what little feed and water they have. ",
          "title": {
            "children": "Kangaroos add pressure on drought-hit farmers by eating scarce feed"
          },
          "imageContainerClassNames": []
        }
      },
      {
        "name": "VolumeCard",
        "props": {
          "contentLabels": [],
          "headingClassNames": [],
          "id": "105856064",
          "imagePosition": {
            "mobile": "right",
            "tablet": "left",
            "desktop": "left"
          },
          "isMajor": false,
          "image": {
            "altText": "a small bird",
            "imgSrc": "https://live-production.wcms.abc-cdn.net.au/7fcb4d163feca184b9c8b24b5e943597?impolicy=wcms_crop_resize&cropH=512&cropW=768&xPos=58&yPos=0&width=160&height=107",
            "imgRatio": "3x2"
          },
          "link": {
            "to": "/news/2025-10-07/noisy-scrub-birds-return-to-west-cape-howe-national-park/105856064"
          },
          "contentUri": "coremedia://article/105856064",
          "canonicalURL": "https://www.abc.net.au/news/2025-10-07/noisy-scrub-birds-return-to-west-cape-howe-national-park/105856064",
          "video": null,
          "reactKey": "nt-105856064-1",
          "synopsis": "The song of the noisy scrub-bird is being heard in WA's West Cape Howe National Park again, bringing joy to bird enthusiasts everywhere.",
          "title": {
            "children": "Songbird heard for first time since 1890s in WA park"
          },
          "imageContainerClassNames": []
        }
      },
      {
        "name": "VolumeCard",
        "props": {
          "contentLabels": [],
          "headingClassNames": [],
          "id": "105860698",
          "imagePosition": {
            "mobile": "right",
            "tablet": "left",
            "desktop": "left"
          },
          "isMajor": false,
          "image": {
            "altText": "Workers in high-vis use handheld drills to break through a large slab of concrete",
            "imgSrc": "https://live-production.wcms.abc-cdn.net.au/29b553ab4d328aa7ca3e57fda3014a08?impolicy=wcms_crop_resize&cropH=2667&cropW=4000&xPos=0&yPos=0&width=160&height=107",
            "imgRatio": "3x2"
          },
          "link": {
            "to": "/news/2025-10-06/indonesia-school-collapse-kills-at-least-63-people/105859952"
          },
          "contentUri": "coremedia://article/105860698",
          "canonicalURL": "https://www.abc.net.au/news/2025-10-06/indonesia-school-collapse-kills-at-least-63-people/105859952",
          "video": null,
          "reactKey": "nt-105860698-1",
          "synopsis": "The number of people killed in the disaster could still rise, with some half a dozen children still unaccounted for.",
          "title": {
            "children": "At least 63 killed in Indonesian school collapse with others still missing"
          },
          "imageContainerClassNames": []
        }
      },
      {
        "name": "VolumeCard",
        "props": {
          "contentLabels": [],
          "headingClassNames": [],
          "id": "105859764",
          "imagePosition": {
            "mobile": "right",
            "tablet": "left",
            "desktop": "left"
          },
          "isMajor": false,
          "image": {
            "altText": "A prison fence and security camera",
            "imgSrc": "https://live-production.wcms.abc-cdn.net.au/19bc76317fcd536790c904e837886422?impolicy=wcms_crop_resize&cropH=3333&cropW=5000&xPos=0&yPos=0&width=160&height=107",
            "imgRatio": "3x2"
          },
          "link": {
            "to": "/news/2025-10-07/victorias-prison-population-surges-bail-laws/105859764"
          },
          "contentUri": "coremedia://article/105859764",
          "canonicalURL": "https://www.abc.net.au/news/2025-10-07/victorias-prison-population-surges-bail-laws/105859764",
          "video": null,
          "reactKey": "nt-105859764-1",
          "synopsis": "Victoria's prison population has surged by 62 per cent in the last 20 years as the number of accused held on remand triples.",
          "title": {
            "children": "Rise in Victoria's prisoner numbers outpace population growth"
          },
          "imageContainerClassNames": []
        }
      },
      {
        "name": "VolumeCard",
        "props": {
          "contentLabels": [],
          "headingClassNames": [],
          "id": "105858164",
          "imagePosition": {
            "mobile": "right",
            "tablet": "left",
            "desktop": "left"
          },
          "isMajor": false,
          "image": {
            "altText": "A portrait of Scott McDougall wearing a suit jacket, white shirt and light blue tie in front of a green background.",
            "imgSrc": "https://live-production.wcms.abc-cdn.net.au/8f33b877ddf45e4508a0652d1c3103a8?impolicy=wcms_crop_resize&cropH=1748&cropW=2622&xPos=1&yPos=0&width=160&height=107",
            "imgRatio": "3x2"
          },
          "link": {
            "to": "/news/2025-10-07/qld-human-rights-commissioner-children-held-in-watch-houses/105858164"
          },
          "contentUri": "coremedia://article/105858164",
          "canonicalURL": "https://www.abc.net.au/news/2025-10-07/qld-human-rights-commissioner-children-held-in-watch-houses/105858164",
          "video": null,
          "reactKey": "nt-105858164-1",
          "synopsis": "Queensland's outgoing human rights commissioner says he has lost sleep worrying about some juveniles \"spending weeks and weeks\" in the state's watch houses.",
          "title": {
            "children": "Boy's 'haunting' expression in watch house drives home concerns for commissioner"
          },
          "imageContainerClassNames": []
        }
      }
    ],
    "major": null
  }
]
